activitypub/__init__.py
activitypub/_version.py
activitypub/classes.py
activitypub/json.py
activitypub/manager.py
activitypub/backup/__init__.py
activitypub/backup/app.py
activitypub/backup/models.py
activitypub/bson/__init__.py
activitypub/bson/errors.py
activitypub/bson/objectid.py
activitypub/bson/py3compat.py
activitypub/bson/tz_util.py
activitypub/database/__init__.py
activitypub/database/base.py
activitypub/database/dummy.py
activitypub/database/listdb.py
activitypub/database/mongodb.py
activitypub/database/redisdb.py
activitypub/database/sqldb.py
activitypub/manager/__init__.py
activitypub/manager/ap_routes.py
activitypub/manager/base.py
activitypub/manager/flaskman.py
activitypub/manager/tornadoman.py
activitypub-0.0.3.dist-info/LICENSE.txt
activitypub-0.0.3.dist-info/METADATA
activitypub-0.0.3.dist-info/RECORD
activitypub-0.0.3.dist-info/WHEEL
activitypub-0.0.3.dist-info/top_level.txt
