Metadata-Version: 1.1
Name: activitypub
Version: 0.0.3
Summary: A general Python ActivityPub library
Home-page: https://github.com/dsblank/activitypub
Author: Douglas S. Blank
Author-email: doug.blank@gmail.com
License: UNKNOWN
Platform: UNKNOWN
Classifier: Framework :: IPython
Classifier: License :: OSI Approved :: GNU Affero General Public License v3 or later (AGPLv3+)
Classifier: Programming Language :: Python :: 3
